nicksutils/__init__.py
nicksutils-0.0.2.dist-info/METADATA
nicksutils-0.0.2.dist-info/WHEEL
nicksutils-0.0.2.dist-info/licenses/LICENSE
nicksutils-0.0.2.dist-info/RECORD
