Metadata-Version: 2.4
Name: nicksutils
Version: 0.0.2
Summary: base utils for python
Project-URL: Homepage, https://github.com/nicks-technik/nicksutils
Project-URL: Issues, https://github.com/nicks-technik/nicksutils/issues
Author-email: Nick Horn <nick2faktor@gmail.com>
License-File: LICENSE
Classifier: License :: OSI Approved :: MIT License
Classifier: Operating System :: OS Independent
Classifier: Programming Language :: Python :: 3
Requires-Python: >=3.0
